hkvsobekpy/__init__.py
hkvsobekpy/__main__.py
hkvsobekpy/core/__init__.py
hkvsobekpy/core/plausibility.py
hkvsobekpy/core/utils.py
hkvsobekpy/core/waterlevelstat.py
hkvsobekpy/io/__init__.py
hkvsobekpy/io/bui.py
hkvsobekpy/io/his.py
hkvsobekpy-1.5.dist-info/LICENSE
hkvsobekpy-1.5.dist-info/WHEEL
hkvsobekpy-1.5.dist-info/METADATA
hkvsobekpy-1.5.dist-info/RECORD
