Metadata-Version: 2.1
Name: hkvsobekpy
Version: 1.5
Summary: package for water-statistics and plausibility checker using his- and bui-file
Home-page: https://www.hkv.nl
License: UNKNOWN
Author: HKV
Author-email: hoek@hkv.nl
Classifier: License :: OSI Approved :: GNU General Public License v3 or later (GPLv3+)
